afifo_cyc.v
module fifo (
    input WR_clk , R_clk, reset_WR, reset_R , WR_EN , R_EN ,
    input [11:0] data_in,
    output reg FULL_WR , EMPTY_R 
);


reg  [2:0] R_PTR_bin , WR_PTR_bin ;
wire [2:0] R_PTR_gry , WR_PTR_gry , R_to_WR_PTR_2_bin , WR_to_R_PTR_2_bin;


reg  [2:0] WR_to_R_PTR_1, WR_to_R_PTR_2 , R_to_WR_PTR_1 , R_to_WR_PTR_2 ;


reg [11:0] ff [7:0];
reg [7:0] mem [15:0];

// gray code block :

assign WR_PTR_gry[2]=WR_PTR_bin[2] ;
assign WR_PTR_gry[1]=WR_PTR_bin[1] ^ WR_PTR_bin[2];
assign WR_PTR_gry[0]=WR_PTR_bin[0] ^ WR_PTR_bin[1];

assign R_PTR_gry[2]=R_PTR_bin[2] ;
assign R_PTR_gry[1]=R_PTR_bin[1] ^ R_PTR_bin[2];
assign R_PTR_gry[0]=R_PTR_bin[0] ^ R_PTR_bin[1];


// reconvert the synchronizers output to bin

assign R_to_WR_PTR_2_bin[2]=R_to_WR_PTR_2[2];
assign R_to_WR_PTR_2_bin[1]=R_to_WR_PTR_2[1] ^ R_to_WR_PTR_2_bin[2];
assign R_to_WR_PTR_2_bin[0]=R_to_WR_PTR_2[0] ^ R_to_WR_PTR_2_bin[1];

assign WR_to_R_PTR_2_bin[2]=WR_to_R_PTR_2[2];
assign WR_to_R_PTR_2_bin[1]=WR_to_R_PTR_2[1] ^ WR_to_R_PTR_2_bin[2];
assign WR_to_R_PTR_2_bin[0]=WR_to_R_PTR_2[0] ^ WR_to_R_PTR_2_bin[1];


//%%%%%%% --- synchronizers for both --- %%%%%% //
// write pointer ke read me vajota thruve the read clk :


always @ (negedge R_clk) begin


    if(reset_R) begin

        WR_to_R_PTR_1 <= 0;
        WR_to_R_PTR_2 <= 0;

    end


    else begin

        WR_to_R_PTR_1 <= WR_PTR_gry ; 
        WR_to_R_PTR_2 <= WR_to_R_PTR_1 ;
         
    end


end


// read pointer ke write domain me 


always @ (negedge WR_clk) begin


    if(reset_WR == 1'b1) begin


        R_to_WR_PTR_1 <= 0;
        R_to_WR_PTR_2 <= 0;
        
    end


    else begin

        R_to_WR_PTR_1 <= R_PTR_gry ; 
        R_to_WR_PTR_2 <= R_to_WR_PTR_1 ;
         
    end


end


// write domain things : 


always @ (negedge WR_clk) begin


    if(reset_WR == 1'b1) begin


        WR_PTR_bin <=3'b0 ;
        FULL_WR    <=1'b0 ;


    end


    //full in write :


    FULL_WR <= (WR_PTR_bin + 3'b001 == R_to_WR_PTR_2_bin) ;


    // wriing :


    if((WR_EN) & (!FULL_WR)) begin


        ff[WR_PTR_bin]  <= data_in ;
        WR_PTR_bin <= 3'b001 + WR_PTR_bin ;


    end


end


// read domain things


always @(negedge R_clk) begin


        if(reset_R) begin


            R_PTR_bin <= 3'b0 ;  
            EMPTY_R   <= 1'b1 ;
        
        end


        EMPTY_R <=  ( R_PTR_bin == WR_to_R_PTR_2_bin )  ;


    if(!EMPTY_R & R_EN) begin


        mem[ff[R_PTR_bin][11:8]] <= ff[R_PTR_bin][7:0] ;
        R_PTR_bin <= 3'b001 + R_PTR_bin ;


    end
    end
    
endmodule

tb.v
`include "afifo_cyc.v"
`timescale 1ns/100ps 

module tb();

reg WR_clk,R_clk,WR_EN,R_EN,reset_WR, reset_R ;
reg [11:0] data_in ;

wire FULL_WR , EMPTY_R ;

fifo f1(
    WR_clk , R_clk , reset_WR, reset_R , WR_EN ,R_EN ,data_in , FULL_WR ,  EMPTY_R 
); 


always   #5 WR_clk = ~ WR_clk ;

always #10 R_clk = ~ R_clk ;

initial begin 

    WR_clk = 1'b0 ; R_clk = 1'b0 ;
    $dumpfile("fifo.vcd");
    $dumpvars(0,tb) ;

    #4 reset_R = 1'b1 ; reset_WR = 1'b1 ;
    #50 reset_WR=1'b0 ; reset_R=1'b0 ;
    #10 WR_EN = 1'b1  ; data_in = 12'h101 ;
    #10 data_in = 12'h202 ;
    #10 data_in = 12'h303 ;
    #10 data_in = 12'h402 ;
    #10 data_in = 12'h503 ; R_EN=1'b1 ;
    #10 data_in = 12'h602 ;
    #10 data_in = 12'h703 ;   
    #10 data_in = 12'h808 ;
    #10 WR_EN = 1'b0 ; 
    #30 WR_EN =1'b1 ; 
    #10 data_in = 12'h908 ; 
    #20 WR_EN = 1'b0 ;    
    #10  

    #150 $display("data in mem 1 %d 2 %d 3 %d 8 %d  fifo me 1 %d 7 %d 0 %d  " ,
             f1.mem[8] , f1.mem[2] , f1.mem[3] , f1.mem[9] , f1.ff[2]  ,f1.ff[7] , f1.ff[0]) ;
    #30 $finish ;

    end
endmodule

fifo.vcd
$date
	Tue Mar 17 21:45:08 2026
$end
$version
	Icarus Verilog
$end
$timescale
	100ps
$end
$scope module tb $end
$var wire 1 ! FULL_WR $end
$var wire 1 " EMPTY_R $end
$var reg 1 # R_EN $end
$var reg 1 $ R_clk $end
$var reg 1 % WR_EN $end
$var reg 1 & WR_clk $end
$var reg 12 ' data_in [11:0] $end
$var reg 1 ( reset_R $end
$var reg 1 ) reset_WR $end
$scope module f1 $end
$var wire 1 # R_EN $end
$var wire 1 $ R_clk $end
$var wire 1 % WR_EN $end
$var wire 1 & WR_clk $end
$var wire 12 * data_in [11:0] $end
$var wire 1 ( reset_R $end
$var wire 1 ) reset_WR $end
$var wire 3 + WR_to_R_PTR_2_bin [2:0] $end
$var wire 3 , WR_PTR_gry [2:0] $end
$var wire 3 - R_to_WR_PTR_2_bin [2:0] $end
$var wire 3 . R_PTR_gry [2:0] $end
$var reg 1 " EMPTY_R $end
$var reg 1 ! FULL_WR $end
$var reg 3 / R_PTR_bin [2:0] $end
$var reg 3 0 R_to_WR_PTR_1 [2:0] $end
$var reg 3 1 R_to_WR_PTR_2 [2:0] $end
$var reg 3 2 WR_PTR_bin [2:0] $end
$var reg 3 3 WR_to_R_PTR_1 [2:0] $end
$var reg 3 4 WR_to_R_PTR_2 [2:0] $end
$upscope $end
$upscope $end
$enddefinitions $end
$comment Show the parameter values. $end
$dumpall
$end
#0
$dumpvars
bx 4
bx 3
bx 2
bx 1
bx 0
bx /
bx .
bx -
bx ,
bx +
bx *
x)
x(
bx '
0&
x%
0$
x#
x"
x!
$end
#40
1)
1(
#50
1&
#100
b0 ,
b0 -
x!
b0 2
b0 1
b0 0
0&
1$
#150
1&
#200
b0 .
b0 +
0!
x"
b0 /
b0 4
b0 3
0&
0$
#250
1&
#300
0&
1$
#350
1&
#400
1"
0&
0$
#450
1&
#500
0&
1$
#540
0(
0)
#550
1&
#600
0&
0$
#640
b100000001 '
b100000001 *
1%
#650
1&
#700
b1 ,
b1 2
0&
1$
#740
b1000000010 '
b1000000010 *
#750
1&
#800
b11 ,
b10 2
b1 3
0&
0$
#840
b1100000011 '
b1100000011 *
#850
1&
#900
b10 ,
b11 2
0&
1$
#940
b10000000010 '
b10000000010 *
#950
1&
#1000
b1 +
b110 ,
b100 2
b1 4
b10 3
0&
0$
#1040
1#
b10100000011 '
b10100000011 *
#1050
1&
#1100
b111 ,
b101 2
0&
1$
#1140
b11000000010 '
b11000000010 *
#1150
1&
#1200
b101 ,
b11 +
b110 2
b10 4
b111 3
0"
0&
0$
#1240
b11100000011 '
b11100000011 *
#1250
1&
#1300
b100 ,
b111 2
0&
1$
#1340
b100000001000 '
b100000001000 *
#1350
1&
#1400
b1 .
b0 ,
b101 +
b0 2
1!
b1 /
b111 4
b100 3
0&
0$
#1440
0%
#1450
1&
#1500
0!
b1 0
0&
1$
#1550
1&
#1600
b1 -
b111 +
b11 .
b1 1
b100 4
b0 3
b10 /
0&
0$
#1650
1&
#1700
1!
b11 0
0&
1$
#1740
1%
#1750
1&
#1800
b10 -
b10 .
b0 +
b11 1
b11 /
b0 4
0&
0$
#1840
b100100001000 '
b100100001000 *
#1850
1&
#1900
0!
b10 0
0&
1$
#1950
1&
#2000
b11 -
b1 ,
b110 .
b10 1
b1 2
b100 /
0&
0$
#2040
0%
#2050
1&
#2100
b110 0
0&
1$
#2150
1&
#2200
b111 .
b100 -
b110 1
b101 /
b1 3
0&
0$
#2250
1&
#2300
b111 0
0&
1$
#2350
1&
#2400
b101 -
b1 +
b101 .
b111 1
b1 4
b110 /
0&
0$
#2450
1&
#2500
b101 0
0&
1$
#2550
1&
#2600
b110 -
b100 .
b101 1
b111 /
0&
0$
#2650
1&
#2700
b100 0
0&
1$
#2750
1&
#2800
b111 -
b0 .
b100 1
b0 /
0&
0$
#2850
1&
#2900
b0 0
0&
1$
#2950
1&
#3000
b1 .
b0 -
b0 1
b1 /
0&
0$
#3050
1&
#3100
b1 0
0&
1$
#3150
1&
#3200
b1 -
b11 .
b1 1
b10 /
1"
0&
0$
#3250
1&
#3300
b11 0
0&
1$
#3350
1&
#3400
b10 -
b11 1
0"
0&
0$
#3450
1&
#3500
1!
0&
1$
#3550
1&
#3600
b10 .
b11 /
0&
0$
#3650
1&
#3700
b10 0
0&
1$
#3750
1&
#3800
b11 -
b110 .
b10 1
b100 /
0&
0$
#3850
1&
#3900
0!
b110 0
0&
1$
