sfifo.v
module fifo(
    input clk,WR_EN,R_EN,reset,
    input [11:0]data_in,
    output reg FULL,EMPTY
);

reg [11:0] ff [7:0];
reg [7:0] mem [15:0];


reg [2:0] R_PTR,WR_PTR ;

always @(negedge clk) begin

    if(reset) begin
        WR_PTR <=3'b0 ; R_PTR <= 3'b0 ; FULL <= 1'b0 ; EMPTY  <= 1'b1 ; 
        end
    
    else begin

      // EMPTY = (WR_PTR == R_PTR);
      // FULL  = ((WR_PTR + 3'b001) == R_PTR);


        /// Wr in to the FIFO 
        // when the WR_EN and !FULL is there you can put data_in ;

        if( !FULL & WR_EN ) begin

            ff[WR_PTR[2:0]] <= data_in ;
            WR_PTR <= 3'b001 + WR_PTR ; ///  THINK WHY WE ARE NOT USING THE  BLOCKING STATE MENT !!!!
        end

        //read when the : so we will put data to the mem 

        if((R_EN) & (!EMPTY) ) begin
            
            mem[ff[R_PTR][11:8]] <= ff[R_PTR][7:0] ;
            R_PTR <= 3'b001 + R_PTR ;

        end

        //EMPTY LA
      
        if(WR_PTR == R_PTR) begin
            EMPTY <= 1;
            FULL  <= 0;
        end
             
        else if( (WR_PTR + 3'b001== R_PTR)) begin  // now i turn all in the circular only simply ::
            EMPTY <= 0;
            FULL  <= 1;
        end

        else begin
            EMPTY <= 0;
            FULL  <= 0;
        end

        //normal simple case can done like this 



    end

    end

endmodule  

/*  FIFO is working fine    problem is that
    
    1 kali address rai ja vandho like in that test bench if R_PTR is 000 and WR_PTR is at 111 so  7 will only  be write if
    you read ptr agaiya vane so  it's ok almost space optimezet !!

    */

tb_sfifo.v
`timescale 1ns/100ps 
`include "sfifo.v"

module tb() ;

    reg clk,R_EN,WR_EN,reset ; 
    reg [11:0] data_in;

    wire FULL,EMPTY ;

    fifo f1(
        clk,WR_EN,R_EN,reset,data_in , FULL , EMPTY
    );

    initial begin 
        clk=1'b0; 
        repeat(100)
        #5 clk = ~ clk ;

    end

    initial begin 


        $dumpfile("sfifo.vcd");
        $dumpvars(0,tb) ;

        R_EN = 0; WR_EN = 0 ;
        #6 reset = 1'b1 ; 
        #10 WR_EN = 1'b1 ;
            data_in =12'h101 ; reset = 1'b0 ;
        #10 data_in =12'h208 ;
        #10 data_in =12'h303 ;
        #10 data_in =12'h404 ;
        #10 data_in =12'h505 ;
        #10 data_in =12'h606 ;
        #10 data_in =12'h707 ;
        #10 data_in =12'h808 ;
        #10 WR_EN = 1'b0 ;  R_EN =1'b1 ; 
        #90 R_EN=1'b0 ; // WR_EN = 1'b1 ; data_in =12'h105 ;
    //  #10 data_in =12'h203 ;
    //  #10 data_in =12'h215 ;
    //  #10 WR_EN = 1'b0 ;  R_EN =1'b1 ; 
        #80 reset=1'b1 ;

        #10 $display("value of mem at 1 %d and at 2 %d at 3 %d ", f1.mem[1] , f1.mem[2] , f1.mem[3] ) ;
        $display("value of mem at 4 %d and at 5 %d at 6 %d ", f1.mem[4] , f1.mem[5] , f1.mem[6] ) ;
        $display("value of mem at 7 %d and fifo jo at 8 %d %d ", f1.mem[7] , f1.ff[0] , f1.mem[1] ) ;
        #60 $finish ;
    
    end
endmodule

sfifo.vcd
$date
	Wed Mar 11 23:45:57 2026
$end
$version
	Icarus Verilog
$end
$timescale
	100ps
$end
$scope module tb $end
$var wire 1 ! FULL $end
$var wire 1 " EMPTY $end
$var reg 1 # R_EN $end
$var reg 1 $ WR_EN $end
$var reg 1 % clk $end
$var reg 12 & data_in [11:0] $end
$var reg 1 ' reset $end
$scope module f1 $end
$var wire 1 # R_EN $end
$var wire 1 $ WR_EN $end
$var wire 1 % clk $end
$var wire 12 ( data_in [11:0] $end
$var wire 1 ' reset $end
$var reg 1 " EMPTY $end
$var reg 1 ! FULL $end
$var reg 3 ) R_PTR [2:0] $end
$var reg 3 * WR_PTR [2:0] $end
$upscope $end
$upscope $end
$enddefinitions $end
$comment Show the parameter values. $end
$dumpall
$end
#0
$dumpvars
bx *
bx )
bx (
x'
bx &
0%
0$
0#
0"
0!
$end
#50
1%
#60
1'
#100
1"
b0 )
b0 *
0%
#150
1%
#160
0'
b100000001 &
b100000001 (
1$
#200
b1 *
0%
#250
1%
#260
b1000001000 &
b1000001000 (
#300
0"
b10 *
0%
#350
1%
#360
b1100000011 &
b1100000011 (
#400
b11 *
0%
#450
1%
#460
b10000000100 &
b10000000100 (
#500
b100 *
0%
#550
1%
#560
b10100000101 &
b10100000101 (
#600
b101 *
0%
#650
1%
#660
b11000000110 &
b11000000110 (
#700
b110 *
0%
#750
1%
#760
b11100000111 &
b11100000111 (
#800
b111 *
0%
#850
1%
#860
b100000001000 &
b100000001000 (
#900
1!
b0 *
0%
#950
1%
#960
1#
0$
#1000
0!
1"
b1 )
0%
#1050
1%
#1100
1!
0"
0%
#1150
1%
#1200
b10 )
0%
#1250
1%
#1300
0!
b11 )
0%
#1350
1%
#1400
b100 )
0%
#1450
1%
#1500
b101 )
0%
#1550
1%
#1600
b110 )
0%
#1650
1%
#1700
b111 )
0%
#1750
1%
#1800
b0 )
0%
#1850
1%
#1860
0#
#1900
1"
0%
#1950
1%
#2000
0%
#2050
1%
#2100
0%
#2150
1%
#2200
0%
#2250
1%
#2300
0%
#2350
1%
#2400
0%
#2450
1%
#2500
0%
#2550
1%
#2600
0%
#2650
1%
#2660
1'
